Puffball/_Puffball.cp39-win_amd64.pyd
Puffball/__init__.py
Puffball-0.0.6.dist-info/LICENSE.txt
Puffball-0.0.6.dist-info/METADATA
Puffball-0.0.6.dist-info/WHEEL
Puffball-0.0.6.dist-info/top_level.txt
Puffball-0.0.6.dist-info/RECORD
