Metadata-Version: 2.1
Name: Puffball
Version: 0.0.6
Summary: Continuous global optimization with non-convex constraints.
Author: Anatoly Filatov
Author-email: anatoly.filatov@outlook.com
License: UNKNOWN
Keywords: puffball,global optimization
Platform: UNKNOWN
License-File: LICENSE.txt
